nterm/__init__.py
nterm/__main__.py
nterm/config.py
nterm/resources.py
nterm/askpass/__init__.py
nterm/askpass/server.py
nterm/connection/__init__.py
nterm/connection/profile.py
nterm/manager/__init__.py
nterm/manager/connect_dialog.py
nterm/manager/editor.py
nterm/manager/io.py
nterm/manager/models.py
nterm/manager/settings.py
nterm/manager/tree.py
nterm/parser/__init__.py
nterm/parser/api_help_dialog.py
nterm/parser/ntc_download_dialog.py
nterm/parser/tfsm_engine.py
nterm/parser/tfsm_fire.py
nterm/parser/tfsm_fire_tester.py
nterm/scripting/__init__.py
nterm/scripting/api.py
nterm/scripting/cli.py
nterm/scripting/models.py
nterm/scripting/platform_data.py
nterm/scripting/platform_utils.py
nterm/scripting/repl.py
nterm/scripting/repl_interactive.py
nterm/scripting/ssh_connection.py
nterm/scripting/test_api_repl.py
nterm/session/__init__.py
nterm/session/askpass_ssh.py
nterm/session/base.py
nterm/session/interactive_ssh.py
nterm/session/local_terminal.py
nterm/session/pty_transport.py
nterm/session/ssh.py
nterm/terminal/__init__.py
nterm/terminal/bridge.py
nterm/terminal/widget.py
nterm/terminal/resources/terminal.html
nterm/terminal/resources/terminal.js
nterm/terminal/resources/xterm-addon-fit.min.js
nterm/terminal/resources/xterm-addon-unicode11.min.js
nterm/terminal/resources/xterm-addon-web-links.min.js
nterm/terminal/resources/xterm.css
nterm/terminal/resources/xterm.min.js
nterm/theme/__init__.py
nterm/theme/engine.py
nterm/theme/stylesheet.py
nterm/theme/themes/clean.yaml
nterm/theme/themes/default.yaml
nterm/theme/themes/dracula.yaml
nterm/theme/themes/enterprise_dark.yaml
nterm/theme/themes/enterprise_hybrid.yaml
nterm/theme/themes/enterprise_light.yaml
nterm/theme/themes/gruvbox_dark.yaml
nterm/theme/themes/gruvbox_hybrid.yaml
nterm/theme/themes/gruvbox_light.yaml
nterm/theme/themes/nord_hybrid.yaml
nterm/vault/__init__.py
nterm/vault/credential_manager.py
nterm/vault/keychain.py
nterm/vault/manager_ui.py
nterm/vault/profile.py
nterm/vault/resolver.py
ntermqt-0.1.9.dist-info/METADATA
ntermqt-0.1.9.dist-info/WHEEL
ntermqt-0.1.9.dist-info/entry_points.txt
ntermqt-0.1.9.dist-info/top_level.txt
ntermqt-0.1.9.dist-info/RECORD
