Metadata-Version: 2.4
Name: ntermqt
Version: 0.1.9
Summary: Modern SSH terminal widget for PyQt6 with credential vault and jump host support
Author: Scott Peterman
License: GPL-3.0
Project-URL: Homepage, https://github.com/scottpeterman/nterm
Project-URL: Repository, https://github.com/scottpeterman/nterm
Project-URL: Issues, https://github.com/scottpeterman/nterm/issues
Keywords: ssh,terminal,pyqt6,network,automation
Classifier: Development Status :: 4 - Beta
Classifier: Environment :: X11 Applications :: Qt
Classifier: Intended Audience :: System Administrators
Classifier: License :: OSI Approved :: GNU General Public License v3 (GPLv3)
Classifier: Operating System :: OS Independent
Classifier: Programming Language :: Python :: 3.10
Classifier: Programming Language :: Python :: 3.11
Classifier: Programming Language :: Python :: 3.12
Classifier: Topic :: System :: Networking
Classifier: Topic :: Terminals :: Terminal Emulators/X Terminals
Requires-Python: >=3.10
Requires-Dist: PyQt6>=6.4.0
Requires-Dist: PyQt6-WebEngine>=6.4.0
Requires-Dist: paramiko>=3.0.0
Requires-Dist: cryptography>=41.0.0
Requires-Dist: pyyaml>=6.0
Requires-Dist: click>=8.0.0
Requires-Dist: ipython>=8.0.0
Requires-Dist: requests>=2.10.0
Requires-Dist: textfsm>=2.0.0
Requires-Dist: rich>=14.0.0
Requires-Dist: pexpect>=4.8.0; sys_platform != "win32"
Requires-Dist: pywinpty>=2.0.0; sys_platform == "win32"
Provides-Extra: keyring
Requires-Dist: keyring>=24.0.0; extra == "keyring"
Provides-Extra: dev
Requires-Dist: pytest; extra == "dev"
Requires-Dist: black; extra == "dev"
Requires-Dist: pyinstaller; extra == "dev"
Requires-Dist: build; extra == "dev"
Requires-Dist: twine; extra == "dev"
Provides-Extra: all
Requires-Dist: keyring>=24.0.0; extra == "all"
